uwulang/__init__.py
uwulang/__main__.py
uwulang-1.0.0.dist-info/METADATA
uwulang-1.0.0.dist-info/WHEEL
uwulang-1.0.0.dist-info/top_level.txt
uwulang-1.0.0.dist-info/RECORD
