Metadata-Version: 2.4
Name: uwulang
Version: 1.0.0
Summary: UwU
Author: kanderusss
Dynamic: author
Dynamic: description
Dynamic: description-content-type
Dynamic: summary
